README.md
setup.py
minitools/__base64.py
minitools/__datetime.py
minitools/__dict.py
minitools/__email.py
minitools/__hashlib.py
minitools/__html.py
minitools/__init__.py
minitools/__json.py
minitools/__logging.py
minitools/__path.py
minitools/__url.py
minitools/__utils.py
minitools/__xpather.py
minitools/version.py
minitools.egg-info/PKG-INFO
minitools.egg-info/SOURCES.txt
minitools.egg-info/dependency_links.txt
minitools.egg-info/top_level.txt
minitools/baidu/__init__.py
minitools/baidu/ocr/__init__.py
minitools/baidu/ocr/__ocr.py
minitools/datastructure/__init__.py
minitools/datastructure/singlylinkedlist.py
minitools/datastructure/twowaylinkedlist.py
minitools/db/__init__.py
minitools/db/amqp/__init__.py
minitools/db/amqp/rabbitmq/__init__.py
minitools/db/mongodb/__init__.py
minitools/db/mongodb/__json.py
minitools/db/mongodb/mongodb.py
minitools/db/mongodb/mongodb_functions.py
minitools/db/redisdb/__init__.py
minitools/db/redisdb/redisdb.py
minitools/github/__init__.py
minitools/github/base.py
minitools/github/blog/__init__.py
minitools/github/blog/blog.py
minitools/github/blog/gather.py
minitools/github/blog/template.py
minitools/github/commits/__init__.py
minitools/javascript/__init__.py
minitools/javascript/__jsl_clearance.py
minitools/javascript/__sojsonv5.py
minitools/javascript/__yunsuoautojump.py
minitools/ml/__init__.py
minitools/ml/base.py
minitools/ml/dtree/__init__.py
minitools/ml/knn/__init__.py
minitools/ml/naivebayes/__init__.py
minitools/ml/netural_network/__init__.py
minitools/ml/svm/__init__.py
minitools/picture/__init__.py
minitools/picture/ziru/__init__.py
minitools/scrapy/__init__.py
minitools/scrapy/__pager.py
minitools/scrapy/__template.py
minitools/scrapy/__utils.py
minitools/scrapy/downloadermiddlewares/__init__.py
minitools/scrapy/downloadermiddlewares/jsl_clearance.py
minitools/scrapy/downloadermiddlewares/proxy_manager.py
minitools/scrapy/extensions/__init__.py
minitools/scrapy/extensions/closespiderwithoutincrement.py
minitools/scrapy/pipelines/__init__.py
minitools/scrapy/pipelines/mongodb_pipeline.py
minitools/scrapy/spiderloader/__init__.py
