Metadata-Version: 1.1
Name: minitools
Version: 0.0.11
Summary: This is a minitools for python
Home-page: https://github.com/CzaOrz/MiniTools
Author: czaOrz
Author-email: chenziangsg@163.com
License: UNKNOWN
Platform: UNKNOWN
Classifier: Programming Language :: Python :: 3
